treescriptify/__init__.py
treescriptify/__main__.py
treescriptify/file_tree.py
treescriptify/script_writer.py
treescriptify/data/__init__.py
treescriptify/data/input_data.py
treescriptify/data/tree_node_data.py
treescriptify/input/__init__.py
treescriptify/input/argument_data.py
treescriptify/input/argument_parser.py
treescriptify-0.3.3.dist-info/licenses/LICENSE
treescriptify-0.3.3.dist-info/METADATA
treescriptify-0.3.3.dist-info/WHEEL
treescriptify-0.3.3.dist-info/entry_points.txt
treescriptify-0.3.3.dist-info/top_level.txt
treescriptify-0.3.3.dist-info/RECORD
