Metadata-Version: 2.4
Name: treescriptify
Version: 0.3.3
Summary: Create TreeScript from an existing filesystem tree.
Home-page: https://github.com/DK96-OS/treescriptify
Author: DK96-OS
License: GPLv3
Project-URL: Issues, https://github.com/DK96-OS/treescriptify/issues
Project-URL: Source Code, https://github.com/DK96-OS/treescriptify
Keywords: treescript
Classifier: Natural Language :: English
Classifier: Operating System :: OS Independent
Classifier: Intended Audience :: Developers
Classifier: License :: OSI Approved :: GNU General Public License v3 (GPLv3)
Classifier: Programming Language :: Python :: 3
Classifier: Programming Language :: Python :: 3.10
Classifier: Programming Language :: Python :: 3.11
Classifier: Programming Language :: Python :: 3.12
Classifier: Programming Language :: Python :: 3.13
Requires-Python: >=3.10
License-File: LICENSE
Dynamic: author
Dynamic: classifier
Dynamic: description
Dynamic: description-content-type
Dynamic: home-page
Dynamic: keywords
Dynamic: license
Dynamic: license-file
Dynamic: project-url
Dynamic: requires-python
Dynamic: summary
